odoo/addons/sale_input_barcode_gs1/README.rst
odoo/addons/sale_input_barcode_gs1/__init__.py
odoo/addons/sale_input_barcode_gs1/__manifest__.py
odoo/addons/sale_input_barcode_gs1/i18n/sale_input_barcode_gs1.pot
odoo/addons/sale_input_barcode_gs1/models/__init__.py
odoo/addons/sale_input_barcode_gs1/models/product_barcode_line_mixin.py
odoo/addons/sale_input_barcode_gs1/readme/CONFIGURE.rst
odoo/addons/sale_input_barcode_gs1/readme/CONTIBUTORS.rst
odoo/addons/sale_input_barcode_gs1/readme/DESCRIPTION.rst
odoo/addons/sale_input_barcode_gs1/static/description/icon.png
odoo/addons/sale_input_barcode_gs1/static/description/index.html
odoo/addons/sale_input_barcode_gs1/tests/__init__.py
odoo/addons/sale_input_barcode_gs1/tests/test_sale_input_barcode_gs1.py
odoo14_addon_sale_input_barcode_gs1-14.0.2.0.0.dist-info/METADATA
odoo14_addon_sale_input_barcode_gs1-14.0.2.0.0.dist-info/WHEEL
odoo14_addon_sale_input_barcode_gs1-14.0.2.0.0.dist-info/top_level.txt
odoo14_addon_sale_input_barcode_gs1-14.0.2.0.0.dist-info/RECORD
