Metadata-Version: 2.1
Name: odoo14-addon-sale-input-barcode-gs1
Version: 14.0.2.0.0
Summary: Add Sale line with barcode using GS1 barcodes
Home-page: https://github.com/OCA/stock-logistics-barcode
Author: Akretion, Odoo Community Association (OCA)
Author-email: support@odoo-community.org
License: AGPL-3
Platform: UNKNOWN
Classifier: Programming Language :: Python
Classifier: Framework :: Odoo
Classifier: Framework :: Odoo :: 14.0
Classifier: License :: OSI Approved :: GNU Affero General Public License v3
Requires-Python: >=3.6
Requires-Dist: odoo14-addon-base-gs1-barcode
Requires-Dist: odoo14-addon-sale-input-barcode
Requires-Dist: odoo <14.1dev,>=14.0a
